looseversion/__init__.py
looseversion/__init__.pyi
looseversion/py.typed
looseversion-1.1.1.dist-info/METADATA
looseversion-1.1.1.dist-info/WHEEL
looseversion-1.1.1.dist-info/licenses/LICENSE
looseversion-1.1.1.dist-info/RECORD
