Metadata-Version: 2.1
Name: looseversion
Version: 1.1.1
Summary: Version numbering for anarchists and software realists
Project-URL: Homepage, https://github.com/effigies/looseversion
Maintainer-email: Chris Markiewicz <effigies@gmail.com>
License: PYTHON SOFTWARE FOUNDATION LICENSE VERSION 2
License-File: LICENSE
Classifier: Development Status :: 6 - Mature
Classifier: License :: OSI Approved :: Python Software Foundation License
Classifier: Programming Language :: Python :: 3
Requires-Python: >=3
